soundcard/__init__.py
soundcard/coreaudio.py
soundcard/coreaudio.py.h
soundcard/coreaudioconstants.py
soundcard/mediafoundation.py
soundcard/mediafoundation.py.h
soundcard/pulseaudio.py
soundcard/pulseaudio.py.h
soundcard/__pyinstaller/__init__.py
soundcard/__pyinstaller/conftest.py
soundcard/__pyinstaller/hook-soundcard.py
soundcard/__pyinstaller/test_soundcard.py
SoundCard-0.4.2.dist-info/LICENSE
SoundCard-0.4.2.dist-info/METADATA
SoundCard-0.4.2.dist-info/WHEEL
SoundCard-0.4.2.dist-info/entry_points.txt
SoundCard-0.4.2.dist-info/top_level.txt
SoundCard-0.4.2.dist-info/RECORD
